[
    {
        "name": "abhinav",
        "position": "Backend Developer",
        "description": "Lorem Ipsum is simply dummy text of the printing and typesetting industry.Lorem Ipsum has been the industry's standard dummy text ever since the 1500s,"
    },
    {
        "name": "Baibhav",
        "position": "Biztalk Developer",
        "description": "चिदंश उनको प्रदान मुख्यतह पुर्णता सुचना भारत क्षमता अनुवाद उपलब्धता जानते उनके निरपेक्ष यन्त्रालय भीयह कार्य अनुकूल अनुवादक प्रोत्साहित हमारि जोवे द्वारा वेबजाल बढाता स्थिति वातावरण संभव पेदा गुजरना खरिदने विशेष कार्य रखति रहारुप निर्देश"
    },
    {
        "name": "Deepshikha",
        "position": "Environmentalist",
        "description": "चिदंश उनको प्रदान मुख्यतह पुर्णता सुचना भारत क्षमता अनुवाद उपलब्धता जानते उनके निरपेक्ष यन्त्रालय भीयह कार्य अनुकूल अनुवादक प्रोत्साहित हमारि जोवे द्वारा वेबजाल बढाता स्थिति वातावरण संभव पेदा गुजरना खरिदने विशेष कार्य रखति रहारुप निर्देश"
    },
    {
        "name": "Ankit Kumar",
        "position": "DotNet Develoepr",
        "description": "चिदंश उनको प्रदान मुख्यतह पुर्णता सुचना भारत क्षमता अनुवाद उपलब्धता जानते उनके निरपेक्ष यन्त्रालय भीयह कार्य अनुकूल अनुवादक प्रोत्साहित हमारि जोवे द्वारा वेबजाल बढाता स्थिति वातावरण संभव पेदा गुजरना खरिदने विशेष कार्य रखति रहारुप निर्देश"
    },
    {
        "name": "Adarsh",
        "position": "Middleware Developer",
        "description": "चिदंश उनको प्रदान मुख्यतह पुर्णता सुचना भारत क्षमता अनुवाद उपलब्धता जानते उनके निरपेक्ष यन्त्रालय भीयह कार्य अनुकूल अनुवादक प्रोत्साहित हमारि जोवे द्वारा वेबजाल बढाता स्थिति वातावरण संभव पेदा गुजरना खरिदने विशेष कार्य रखति रहारुप निर्देश"
    },
    {
        "name": "Ravindra",
        "position": "Accontant",
        "description": "चिदंश उनको प्रदान मुख्यतह पुर्णता सुचना भारत क्षमता अनुवाद उपलब्धता जानते उनके निरपेक्ष यन्त्रालय भीयह कार्य अनुकूल अनुवादक प्रोत्साहित हमारि जोवे द्वारा वेबजाल बढाता स्थिति वातावरण संभव पेदा गुजरना खरिदने विशेष कार्य रखति रहारुप निर्देश"
    }
]